gethwp/__init__.py
gethwp-1.0.0.dist-info/LICENSE
gethwp-1.0.0.dist-info/METADATA
gethwp-1.0.0.dist-info/WHEEL
gethwp-1.0.0.dist-info/top_level.txt
gethwp-1.0.0.dist-info/RECORD
